{"document_vue_faq.md":"15ef8d98","document_vue_vue.md":"a4a51209","document_vue_vue3.md":"914e50dc","document_css_css.md":"2241e7e2","document_git_faq.md":"138c0eed","document_git_git.md":"f7017619","document_html_html.md":"d0634c75","document_javascript_js-array.md":"58e629f2","document_javascript_js-string.md":"2d968823","document_javascript_js-traversal-method.md":"d582b7ce","document_nginx_nginx.md":"5e09f100","document_typescript_faq.md":"1acba095","document_typescript_typescript.md":"3694bf80","en-us_index.md":"64d5e7cd","guide_index.md":"caf29c80","index.md":"f9ea0304","note_ecmascript6_iterator.md":"2c857021","note_ecmascript6_module.md":"283779df","note_ecmascript6_promise.md":"74625593","note_ecmascript6_proxy.md":"8dd639fd","note_ecmascript6_index.md":"76dbe95f","note_javascript_functionmethods.md":"a3a1dad7","note_javascript_objectoriented.md":"77bbe4bf","note_javascript_referencetype.md":"227c173d","note_javascript_index.md":"e82468a7","note_thymeleaf_basesyntax.md":"9152ac22","note_thymeleaf_index.md":"c08c0c1f"}
